LICENSE
MANIFEST.in
README.md
requirements.txt
setup.py
cert_verifier/__init__.py
cert_verifier/checks.py
cert_verifier/connectors.py
cert_verifier/errors.py
cert_verifier/verifier.py
cert_verifier.egg-info/PKG-INFO
cert_verifier.egg-info/SOURCES.txt
cert_verifier.egg-info/dependency_links.txt
cert_verifier.egg-info/requires.txt
cert_verifier.egg-info/top_level.txt
tests/__init__.py
tests/test_checks.py
tests/test_connectors.py
tests/test_verifier.py