Metadata-Version: 1.0
Name: cert-verifier
Version: 2.0.15
Summary: Verifies blockchain certificates
Home-page: https://github.com/blockchain-certificates/cert-verifier
Author: Blockcerts
Author-email: info@blockcerts.org
License: MIT
Platform: UNKNOWN
